sgu_client/__init__.py
sgu_client/client/__init__.py
sgu_client/client/base.py
sgu_client/client/chemistry/__init__.py
sgu_client/client/chemistry/chemistry.py
sgu_client/client/levels/__init__.py
sgu_client/client/levels/modeled.py
sgu_client/client/levels/observed.py
sgu_client/config.py
sgu_client/exceptions.py
sgu_client/models/__init__.py
sgu_client/models/base.py
sgu_client/models/chemistry.py
sgu_client/models/modeled.py
sgu_client/models/observed.py
sgu_client/models/shared.py
sgu_client/py.typed
sgu_client/sgu_client.py
sgu_client/utils/__init__.py
sgu_client/utils/pandas_helpers.py
sgu_client-0.4.3.dist-info/WHEEL
sgu_client-0.4.3.dist-info/METADATA
sgu_client-0.4.3.dist-info/RECORD
