Metadata-Version: 2.4
Name: sgu-client
Version: 0.4.3
Summary: A modern Python client library for accessing Geological Survey of Sweden groundwater data APIs with type safety and pandas integration
Author: Anders Retzner
Author-email: Anders Retzner <anders.retzner@gmail.com>
License-Expression: MIT
Requires-Dist: requests>=2.28.0
Requires-Dist: pydantic>=2.0.0
Requires-Dist: pandas>=1.5.0 ; extra == 'recommended'
Requires-Python: >=3.11
Provides-Extra: recommended
